{"cameraMode":{"drawMode":0,"name":"Shaded","section":"Shading Mode"},"sceneLighting":true,"audioPlay":false,"sceneViewState":{"m_AlwaysRefresh":false,"showFog":true,"showSkybox":true,"showFlares":true,"showImageEffects":true,"showParticleSystems":true,"showVisualEffectGraphs":true,"m_FxEnabled":true},"in2DMode":false,"pivot":{"x":0.0,"y":-0.1547050178050995,"z":0.0},"rotation":{"x":-0.17641445994377137,"y":0.32168638706207278,"z":-0.06113622337579727,"w":-0.9282556772232056},"size":1.1785410642623902,"orthographic":false}